sleplet/__init__.py
sleplet/_array_methods.py
sleplet/_bool_methods.py
sleplet/_class_lists.py
sleplet/_convolution_methods.py
sleplet/_integration_methods.py
sleplet/_mask_methods.py
sleplet/_mesh_methods.py
sleplet/_parallel_methods.py
sleplet/_plotly_methods.py
sleplet/_slepian_arbitrary_methods.py
sleplet/_smoothing.py
sleplet/_string_methods.py
sleplet/_validation.py
sleplet/_vars.py
sleplet/_version.py
sleplet/harmonic_methods.py
sleplet/noise.py
sleplet/plot_methods.py
sleplet/py.typed
sleplet/slepian_methods.py
sleplet/wavelet_methods.py
sleplet/_data/__init__.py
sleplet/_data/create_earth_flm.py
sleplet/_data/create_wmap_flm.py
sleplet/_data/meshes_polygons_bird.off
sleplet/_data/meshes_polygons_cheetah.off
sleplet/_data/meshes_polygons_cube.off
sleplet/_data/meshes_polygons_dragon.off
sleplet/_data/meshes_polygons_homer.off
sleplet/_data/meshes_polygons_teapot.off
sleplet/_data/meshes_regions_bird.toml
sleplet/_data/meshes_regions_cheetah.toml
sleplet/_data/meshes_regions_cube.toml
sleplet/_data/meshes_regions_dragon.toml
sleplet/_data/meshes_regions_homer.toml
sleplet/_data/meshes_regions_teapot.toml
sleplet/_data/setup_pooch.py
sleplet/_scripts/__init__.py
sleplet/_scripts/plotting_on_mesh.py
sleplet/_scripts/plotting_on_sphere.py
sleplet/functions/__init__.py
sleplet/functions/africa.py
sleplet/functions/axisymmetric_wavelet_coefficients_africa.py
sleplet/functions/axisymmetric_wavelet_coefficients_earth.py
sleplet/functions/axisymmetric_wavelet_coefficients_south_america.py
sleplet/functions/axisymmetric_wavelets.py
sleplet/functions/coefficients.py
sleplet/functions/dirac_delta.py
sleplet/functions/earth.py
sleplet/functions/elongated_gaussian.py
sleplet/functions/flm.py
sleplet/functions/fp.py
sleplet/functions/gaussian.py
sleplet/functions/harmonic_gaussian.py
sleplet/functions/identity.py
sleplet/functions/noise_earth.py
sleplet/functions/ridgelets.py
sleplet/functions/slepian.py
sleplet/functions/slepian_africa.py
sleplet-1.5.2.dist-info/licenses/LICENCE.txt
sleplet-1.5.2.dist-info/METADATA
sleplet-1.5.2.dist-info/WHEEL
sleplet-1.5.2.dist-info/entry_points.txt
sleplet-1.5.2.dist-info/top_level.txt
sleplet-1.5.2.dist-info/RECORD
