Metadata-Version: 2.4
Name: sleplet
Version: 1.5.2
Summary: Slepian Scale-Discretised Wavelets in Python
Author-email: "Patrick J. Roddy" <patrickjamesroddy@gmail.com>
License-Expression: BSD-3-Clause
Project-URL: Code, https://github.com/astro-informatics/sleplet
Project-URL: Documentation, https://astro-informatics.github.io/sleplet
Project-URL: Download, https://pypi.org/project/sleplet
Project-URL: Homepage, https://github.com/astro-informatics/sleplet
Project-URL: Issues, https://github.com/astro-informatics/sleplet/issues
Keywords: manifolds,python,slepian-functions,sphere,wavelets
Classifier: Operating System :: POSIX
Classifier: Programming Language :: Python :: 3
Classifier: Programming Language :: Python :: 3 :: Only
Classifier: Programming Language :: Python :: 3.11
Classifier: Programming Language :: Python :: 3.12
Classifier: Programming Language :: Python :: 3.13
Classifier: Topic :: Scientific/Engineering :: Image Processing
Classifier: Topic :: Scientific/Engineering :: Mathematics
Classifier: Topic :: Scientific/Engineering :: Physics
Classifier: Topic :: Scientific/Engineering :: Visualization
Classifier: Typing :: Typed
Requires-Python: >=3.11
License-File: LICENCE.txt
Requires-Dist: gmpy2~=2.0
Requires-Dist: hypothesis~=6.0
Requires-Dist: libigl~=2.0
Requires-Dist: matplotlib~=3.0
Requires-Dist: multiprocess~=0.0
Requires-Dist: numba~=0.0
Requires-Dist: numpy~=2.0
Requires-Dist: platformdirs~=4.0
Requires-Dist: plotly~=6.0
Requires-Dist: pooch~=1.0
Requires-Dist: pydantic~=2.0
Requires-Dist: pys2let~=2.0
Requires-Dist: pyssht~=1.0
Requires-Dist: scipy~=1.0
Requires-Dist: seaborn~=0.0
Requires-Dist: tomli~=2.0
Requires-Dist: tqdm~=4.0
Dynamic: license-file
